README.md
setup.py
dsplab/__init__.py
dsplab/filtration.py
dsplab/helpers.py
dsplab/modulation.py
dsplab/player.py
dsplab/prony.py
dsplab/spectran.py
dsplab.egg-info/PKG-INFO
dsplab.egg-info/SOURCES.txt
dsplab.egg-info/dependency_links.txt
dsplab.egg-info/requires.txt
dsplab.egg-info/top_level.txt
dsplab/data/plan-schema.json
dsplab/flow/__init__.py
dsplab/flow/activity.py
dsplab/flow/online.py
dsplab/flow/plan.py
dsplab/flow/verify.py
test/test_filtration.py
test/test_helpers.py
test/test_modulation.py
test/test_player.py
test/test_prony.py
test/test_spectran.py