Metadata-Version: 1.1
Name: dsplab
Version: 0.41.0
Summary:  Dsplab is the package for building generalized signal processing schemes.
Home-page: https://github.com/aleneus/dsplab
Author: Aleksandr Popov, Kirill Butin
Author-email: aleneus@gmail.com
License: LGPLv3
Keywords: digital signal processing
Platform: UNKNOWN
Classifier: Development Status :: 3 - Alpha
Classifier: Environment :: Console
Classifier: Intended Audience :: Science/Research
Classifier: Intended Audience :: Developers
Classifier: License :: OSI Approved :: GNU Lesser General Public License v3 (LGPLv3)
Classifier: Operating System :: POSIX :: Linux
Classifier: Operating System :: Microsoft :: Windows
Classifier: Programming Language :: Python :: 3
Classifier: Topic :: Scientific/Engineering
